{
    "cache_dir": "./cache",
    "gold_standard_configuration": {
        "path": "./tools/datasets/dronology_req_design_hf/answer-req-design-hf.csv",
        "hasHeader": "true"
    },
    "source_artifact_provider": {
        "name": "text",
        "args": {
            "artifact_type": "requirement",
            "path": "./tools/datasets/dronology_req_design_hf/requirements"
        }
    },
    "target_artifact_provider": {
        "name": "text",
        "args": {
            "artifact_type": "design definition",
            "path": "./tools/datasets/dronology_req_design_hf/designs"
        }
    },
    "source_preprocessor": {
        "name": "artifact",
        "args": {}
    },
    "target_preprocessor": {
        "name": "artifact",
        "args": {}
    },
    "embedding_creator": {
        "name": "openwebui",
        "args": {
            "model": "nomic-ai/nomic-embed-text-v1.5:free"
        }
    },
    "source_store": {
        "name": "custom",
        "args": {}
    },
    "target_store": {
        "name": "custom",
        "args": {
            "max_results": "4"
        }
    },
    "classifier": {
        "name": "simple_openwebui",
        "args": {
            "model": "mistralai/mistral-small-3.1-24b-instruct:free"
        }
    },
    "result_aggregator": {
        "name": "any_connection",
        "args": {}
    },
    "tracelinkid_postprocessor": {
        "name": "identity",
        "args": {}
    }
}